version.py
echowarp/__init__.py
echowarp/logging_config.py
echowarp/main.py
echowarp/settings.py
echowarp/auth_and_heartbeat/__init__.py
echowarp/auth_and_heartbeat/transport_base.py
echowarp/auth_and_heartbeat/transport_client.py
echowarp/auth_and_heartbeat/transport_server.py
echowarp/models/__init__.py
echowarp/models/audio_device.py
echowarp/models/ban_list.py
echowarp/models/default_values_and_options.py
echowarp/models/json_message.py
echowarp/models/net_interfaces_info.py
echowarp/models/options_data_creater.py
echowarp/services/__init__.py
echowarp/services/crypto_manager.py
echowarp/start_modes/__init__.py
echowarp/start_modes/args_mode.py
echowarp/start_modes/config_parser.py
echowarp/start_modes/interactive_mode.py
echowarp/streamer/__init__.py
echowarp/streamer/audio_client.py
echowarp/streamer/audio_server.py
echowarp-0.4.0.dist-info/METADATA
echowarp-0.4.0.dist-info/WHEEL
echowarp-0.4.0.dist-info/entry_points.txt
echowarp-0.4.0.dist-info/top_level.txt
echowarp-0.4.0.dist-info/RECORD
