Metadata-Version: 2.1
Name: echowarp
Version: 0.4.0
Summary: Network audio streaming tool using UDP
Home-page: https://github.com/lHumaNl/EchoWarp
Author: lHumaNl
Author-email: fisher_sam@mail.ru
License: MIT
Keywords: audio streaming network
Classifier: Development Status :: 3 - Alpha
Classifier: Intended Audience :: Developers
Classifier: Topic :: Multimedia :: Sound/Audio
Classifier: License :: OSI Approved :: MIT License
Classifier: Programming Language :: Python :: 3
Classifier: Programming Language :: Python :: 3.6
Requires-Dist: PyAudio
Requires-Dist: cryptography
Requires-Dist: chardet
